htchirp/__init__.py
htchirp/__main__.py
htchirp/cli.py
htchirp/htchirp.py
htchirp-3.0.dist-info/LICENSE
htchirp-3.0.dist-info/METADATA
htchirp-3.0.dist-info/WHEEL
htchirp-3.0.dist-info/entry_points.txt
htchirp-3.0.dist-info/top_level.txt
htchirp-3.0.dist-info/RECORD
