Metadata-Version: 2.1
Name: htchirp
Version: 3.0
Summary: Pure Python Chirp client for HTCondor
Home-page: https://htcondor.org
Author: Jason Patton
Author-email: jpatton@cs.wisc.edu
License: ASL 2.0
Project-URL: Bug Reports, https://github.com/htcondor/htchirp/issues
Project-URL: Source, https://github.com/htcondor/htchirp/
Keywords: htcondor chirp
License-File: LICENSE
